echo/VERSION
echo/__init__.py
echo/optimize.py
echo/report.py
echo/run.py
echo/src/__init__.py
echo/src/base_objective.py
echo/src/config.py
echo/src/partial_dependence.py
echo/src/pruners.py
echo/src/reporting.py
echo/src/samplers.py
echo/src/trial_suggest.py
echo_opt-1.2.dist-info/LICENSE
echo_opt-1.2.dist-info/METADATA
echo_opt-1.2.dist-info/WHEEL
echo_opt-1.2.dist-info/entry_points.txt
echo_opt-1.2.dist-info/top_level.txt
echo_opt-1.2.dist-info/zip-safe
echo_opt-1.2.dist-info/RECORD
