Metadata-Version: 2.2
Name: echo-opt
Version: 1.2
Summary: Earth Computer Hyperparameter Optimization: Distributed hyperparameter optimization on HPC and GPU systems with analysis tools.
Home-page: https://github.com/NCAR/echo-opt
Author: John Schreck, David John Gagne, Charlie Becker, Gabrielle Gantos
Author-email: miles@ucar.edu
License: MIT
Keywords: machine-learning,hyperparameter,gpu
Platform: any
Classifier: Programming Language :: Python
Classifier: Programming Language :: Python :: 3.8
Classifier: Programming Language :: Python :: 3.9
Classifier: Programming Language :: Python :: 3.10
Classifier: Programming Language :: Python :: 3.11
Classifier: Programming Language :: Python :: 3.12
Requires-Python: >3.7
License-File: LICENSE
Requires-Dist: numpy
Requires-Dist: scipy
Requires-Dist: matplotlib
Requires-Dist: optuna<4.0
Requires-Dist: setuptools
Requires-Dist: pandas
Requires-Dist: scikit-learn
Requires-Dist: xgboost
Requires-Dist: pyarrow
Requires-Dist: pyyaml
